curlit/__init__.py
curlit/base.py
curlit/django.py
curlit/requests.py
curlit/urllib.py
curlit-0.2.1.dist-info/AUTHORS.rst
curlit-0.2.1.dist-info/LICENSE
curlit-0.2.1.dist-info/METADATA
curlit-0.2.1.dist-info/WHEEL
curlit-0.2.1.dist-info/top_level.txt
curlit-0.2.1.dist-info/RECORD
