Metadata-Version: 2.1
Name: curlit
Version: 0.2.1
Summary: Generate curl commands from various python libraries request objects
Home-page: https://github.com/NorthIsUp/curlit
Author: Adam Hitchcocactk
Author-email: adam@northisup.com
License: UNKNOWN
Platform: UNKNOWN
